odoo/addons/ssi_client_reimbursement/README.rst
odoo/addons/ssi_client_reimbursement/__init__.py
odoo/addons/ssi_client_reimbursement/__manifest__.py
odoo/addons/ssi_client_reimbursement/data/account_journal_data.xml
odoo/addons/ssi_client_reimbursement/data/approval_template_data.xml
odoo/addons/ssi_client_reimbursement/data/base_automation_data.xml
odoo/addons/ssi_client_reimbursement/data/ir_actions_server_data.xml
odoo/addons/ssi_client_reimbursement/data/ir_sequence_data.xml
odoo/addons/ssi_client_reimbursement/data/policy_template_data.xml
odoo/addons/ssi_client_reimbursement/data/sequence_template_data.xml
odoo/addons/ssi_client_reimbursement/models/__init__.py
odoo/addons/ssi_client_reimbursement/models/client_reimbursement.py
odoo/addons/ssi_client_reimbursement/models/client_reimbursement_detail.py
odoo/addons/ssi_client_reimbursement/models/client_reimbursement_type.py
odoo/addons/ssi_client_reimbursement/security/ir.model.access.csv
odoo/addons/ssi_client_reimbursement/security/ir_module_category_data.xml
odoo/addons/ssi_client_reimbursement/security/ir_rule_data.xml
odoo/addons/ssi_client_reimbursement/security/res_group_data.xml
odoo/addons/ssi_client_reimbursement/static/description/icon.png
odoo/addons/ssi_client_reimbursement/static/description/icon_timesheet.png
odoo/addons/ssi_client_reimbursement/views/client_reimbursement_type_views.xml
odoo/addons/ssi_client_reimbursement/views/client_reimbursement_views.xml
odoo14_addon_ssi_client_reimbursement-14.0.1.0.1.dist-info/METADATA
odoo14_addon_ssi_client_reimbursement-14.0.1.0.1.dist-info/WHEEL
odoo14_addon_ssi_client_reimbursement-14.0.1.0.1.dist-info/top_level.txt
odoo14_addon_ssi_client_reimbursement-14.0.1.0.1.dist-info/RECORD
